odoo8_addon_crm_department-8.0.1.0.1-py2.7-nspkg.pth
odoo_addons/crm_department/__openerp__.py
odoo_addons/crm_department/__init__.py
odoo_addons/crm_department/crm_view.xml
odoo_addons/crm_department/README.rst
odoo_addons/crm_department/crm.py
odoo_addons/crm_department/i18n/ru.po
odoo_addons/crm_department/i18n/es.po
odoo_addons/crm_department/i18n/bg.po
odoo_addons/crm_department/i18n/crm_department.pot
odoo8_addon_crm_department-8.0.1.0.1.dist-info/top_level.txt
odoo8_addon_crm_department-8.0.1.0.1.dist-info/WHEEL
odoo8_addon_crm_department-8.0.1.0.1.dist-info/RECORD
odoo8_addon_crm_department-8.0.1.0.1.dist-info/metadata.json
odoo8_addon_crm_department-8.0.1.0.1.dist-info/DESCRIPTION.rst
odoo8_addon_crm_department-8.0.1.0.1.dist-info/METADATA
odoo8_addon_crm_department-8.0.1.0.1.dist-info/namespace_packages.txt
